README.rst
rexmenu.py
setup.py
rexmenu.egg-info/PKG-INFO
rexmenu.egg-info/SOURCES.txt
rexmenu.egg-info/dependency_links.txt
rexmenu.egg-info/requires.txt
rexmenu.egg-info/top_level.txt