Metadata-Version: 1.0
Name: rexmenu
Version: 2.0
Summary: Simple image tiling program launcher/MAME frontend using Pygame
Home-page: https://playermissile.com
Author: Rob McMullen
Author-email: feedback@playermissile.com
License: GPL
Platform: UNKNOWN
